LigBinder-0.1.4.data/data/ligbinder/default_config.yml
LigBinder-0.1.4.data/scripts/ligbinder
ligbinder/__init__.py
ligbinder/core.py
ligbinder/md.py
ligbinder/report.py
ligbinder/settings.py
ligbinder/tree.py
LigBinder-0.1.4.dist-info/LICENSE
LigBinder-0.1.4.dist-info/METADATA
LigBinder-0.1.4.dist-info/WHEEL
LigBinder-0.1.4.dist-info/top_level.txt
LigBinder-0.1.4.dist-info/RECORD
