Metadata-Version: 2.1
Name: LigBinder
Version: 0.1.4
Summary: automatic targeted molecular dynamics for ligand bindning
Home-page: https://github.com/ggutierrez-bio/ligbinder
Author: Guillermo Gutierrez
Author-email: 
License: UNKNOWN
Platform: UNKNOWN
License-File: LICENSE
Requires-Dist: numpy
Requires-Dist: pyyaml
Requires-Dist: pytraj (>=2)
Requires-Dist: parmed
